LICENCE
MANIFEST.in
README.md
setup.py
linkpath/__init__.py
linkpath.egg-info/PKG-INFO
linkpath.egg-info/SOURCES.txt
linkpath.egg-info/dependency_links.txt
linkpath.egg-info/requires.txt
linkpath.egg-info/top_level.txt
scripts/linkpath