Metadata-Version: 1.0
Name: linkpath
Version: 0.1.1
Summary: A Python library for querying the linked data web
Home-page: https://github.com/iand/linkpath
Author: Ian Davis
Author-email: nospam@iandavis.com
License: UNKNOWN
Platform: UNKNOWN
Classifier: Programming Language :: Python
Classifier: License :: Public Domain
Classifier: Operating System :: OS Independent
Classifier: Development Status :: 4 - Beta
Classifier: Intended Audience :: Developers
Classifier: Topic :: Software Development :: Libraries :: Python Modules
Classifier: Topic :: Database
